nnunetv2/__init__.py
nnunetv2/configuration.py
nnunetv2/paths.py
nnunetv2/batch_running/__init__.py
nnunetv2/batch_running/collect_results_custom_Decathlon.py
nnunetv2/batch_running/collect_results_custom_Decathlon_2d.py
nnunetv2/batch_running/generate_lsf_runs_customDecathlon.py
nnunetv2/batch_running/benchmarking/__init__.py
nnunetv2/batch_running/benchmarking/generate_benchmarking_commands.py
nnunetv2/batch_running/benchmarking/summarize_benchmark_results.py
nnunetv2/batch_running/release_trainings/__init__.py
nnunetv2/batch_running/release_trainings/nnunetv2_v1/__init__.py
nnunetv2/batch_running/release_trainings/nnunetv2_v1/collect_results.py
nnunetv2/batch_running/release_trainings/nnunetv2_v1/generate_lsf_commands.py
nnunetv2/dataset_conversion/Dataset027_ACDC.py
nnunetv2/dataset_conversion/Dataset073_Fluo_C3DH_A549_SIM.py
nnunetv2/dataset_conversion/Dataset114_MNMs.py
nnunetv2/dataset_conversion/Dataset115_EMIDEC.py
nnunetv2/dataset_conversion/Dataset120_RoadSegmentation.py
nnunetv2/dataset_conversion/Dataset137_BraTS21.py
nnunetv2/dataset_conversion/Dataset218_Amos2022_task1.py
nnunetv2/dataset_conversion/Dataset219_Amos2022_task2.py
nnunetv2/dataset_conversion/Dataset220_KiTS2023.py
nnunetv2/dataset_conversion/Dataset221_AutoPETII_2023.py
nnunetv2/dataset_conversion/Dataset988_dummyDataset4.py
nnunetv2/dataset_conversion/__init__.py
nnunetv2/dataset_conversion/convert_MSD_dataset.py
nnunetv2/dataset_conversion/convert_raw_dataset_from_old_nnunet_format.py
nnunetv2/dataset_conversion/generate_dataset_json.py
nnunetv2/dataset_conversion/datasets_for_integration_tests/Dataset996_IntegrationTest_Hippocampus_regions_ignore.py
nnunetv2/dataset_conversion/datasets_for_integration_tests/Dataset997_IntegrationTest_Hippocampus_regions.py
nnunetv2/dataset_conversion/datasets_for_integration_tests/Dataset998_IntegrationTest_Hippocampus_ignore.py
nnunetv2/dataset_conversion/datasets_for_integration_tests/Dataset999_IntegrationTest_Hippocampus.py
nnunetv2-2.2.2.dist-info/LICENSE
nnunetv2-2.2.2.dist-info/METADATA
nnunetv2-2.2.2.dist-info/WHEEL
nnunetv2-2.2.2.dist-info/entry_points.txt
nnunetv2-2.2.2.dist-info/top_level.txt
nnunetv2-2.2.2.dist-info/RECORD
